COPYRIGHT.txt
CREDITS.txt
HISTORY.txt
INSTALL.txt
LICENSE.txt
MANIFEST.in
README.rst
VERSION.txt
setup.cfg
setup.py
primer/__init__.py
primer/__main__.py
primer/primer.py
primer.egg-info/PKG-INFO
primer.egg-info/SOURCES.txt
primer.egg-info/dependency_links.txt
primer.egg-info/not-zip-safe
primer.egg-info/top_level.txt
primer/tests/__init__.py
primer/tests/__main__.py
primer/tests/test_primer.py