Metadata-Version: 1.1
Name: primer
Version: 1.4.4
Summary: A primer for prime numbers
Home-page: https://github.com/cbcunc/primer
Author: Chris Calloway
Author-email: cbc@chriscalloway.org
License: GPL2
Download-URL: https://github.com/cbcunc/primer/tarball/1.4.4
Keywords: Prime number primes primorial
Platform: UNKNOWN
Classifier: Development Status :: 5 - Production/Stable
Classifier: License :: OSI Approved :: GNU General Public License v2 (GPLv2)
Classifier: Programming Language :: Python :: 2.7
Classifier: Programming Language :: Python :: 3.4
Classifier: Topic :: Scientific/Engineering :: Mathematics
